Asuraa
