Metadata-Version: 2.1
Name: Asuraa
Version: 0.0.2.7
Summary: Python Api | AsuraaApi
Home-page: https://github.com/itzAsuraa/AsuraaApi
Author: The Caption | itzAsuraa
Author-email: itzAsuraa@gmail.com
License: MIT
Download-URL: https://github.com/itzAsuraa/AsuraaApi/blob/main/README.md
Project-URL: Tracker, https://github.com/itzAsuraa/AsuraaApi/issues
Project-URL: Community, https://t.me/AsuraaSupport
Project-URL: Source, https://github.com/itzAsuraa/AsuraaApi
Keywords: python,Asuraa,flask
Platform: UNKNOWN
Classifier: Development Status :: 5 - Production/Stable
Classifier: Intended Audience :: Developers
Classifier: Natural Language :: English
Classifier: Operating System :: OS Independent
Classifier: Programming Language :: Python
Classifier: Programming Language :: Python :: 3
Classifier: Programming Language :: Python :: 3.7
Classifier: Programming Language :: Python :: 3.8
Classifier: Programming Language :: Python :: 3.9
Classifier: Programming Language :: Python :: 3.10
Classifier: Programming Language :: Python :: 3.11
Classifier: Programming Language :: Python :: 3.12
Classifier: Programming Language :: Python :: Implementation
Classifier: Programming Language :: Python :: Implementation :: CPython
Classifier: Programming Language :: Python :: Implementation :: PyPy
Classifier: Topic :: Internet
Classifier: Topic :: Communications
Classifier: Topic :: Communications :: Chat
Classifier: Topic :: Software Development :: Libraries
Classifier: Topic :: Software Development :: Libraries :: Python Modules
Classifier: Topic :: Software Development :: Libraries :: Application Frameworks
Requires-Python: ~=3.7
